[{
    "name": "Black",
    "artist": "Pearl Jam",
    "album": "Ten",
    "year": "1991",
    "url": "https://www.youtube.com/watch?v=4q9UafsiQ6k",
    "picture": "http://www.grayflannelsuit.net/blog/wp-content/uploads/2011/01/Pearl-Jam-Ten.jpg",
    "status": "idle",
    "votes": 0
},
{
    "name": "Sick Bubblegum",
    "artist": "Rob Zombie",
    "album": "Hellbilly Deluxe 2",
    "year": "2008",
    "url": "https://www.youtube.com/watch?v=AeUwikDrA9I",
    "picture": "https://upload.wikimedia.org/wikipedia/en/f/f6/Rob_zombie_sick_bubblegum.png",
    "status": "idle",
    "votes": 0
},
{
    "name": "Black Ice",
    "artist": "AC/DC",
    "album": "Black Ice",
    "year": "2007",
    "url": "https://www.youtube.com/watch?v=ruBZEJuUmjc",
    "picture": "https://upload.wikimedia.org/wikipedia/en/3/3e/Black_ice_red.jpg",
    "status": "idle",
    "votes": 0
},
{
    "name": "Madness",
    "artist": "Muse",
    "album": "The 2nd Law",
    "year": "2012",
    "url": "https://www.youtube.com/watch?v=6w5KCf8hXvo",
    "picture": "https://upload.wikimedia.org/wikipedia/en/9/9b/Muse_-_Madness.jpg",
    "status": "idle",
    "votes": 0
},
{
    "name": "Without Me",
    "artist": "Eminem",
    "album": "The Eminem Show",
    "year": "2002",
    "url": "https://www.youtube.com/watch?v=YVkUvmDQ3HY",
    "picture": "https://upload.wikimedia.org/wikipedia/en/a/ad/Eminem_-_Without_Me_CD_cover.jpg",
    "status": "idle",
    "votes": 0
},
{
    "name": "King Nothing",
    "artist": "Metallica",
    "album": "Load",
    "year": "1997",
    "url": "https://www.youtube.com/watch?v=oFBbOHohwR8",
    "picture": "https://upload.wikimedia.org/wikipedia/en/3/3d/Metallica_-_King_Nothing_cover.jpg",
    "status": "idle",
    "votes": 0
}]